[{"name": "5-Way Ph\u00edm \u0110i\u1ec1u H\u01b0\u1edbng 5 C\u1eeda SMD", "img": "https://www.thegioiic.com/upload/medium/21895.jpg", "mfr": "OEM", "price": "4.000 \u0111/C\u00e1i", "stock": "H\u00e0ng c\u00f2n: 836", "link": "https://www.thegioiic.com/5-way-phim-dieu-huong-5-cua-smd", "desc": "Rating: 20mA 12VDC", "detail": "<div class=\"mt-4 pt-2 bg-white\">\n\n<div class=\"mt-2 text-medium-s body-tab\">\n<table border=\"1\" cellpadding=\"0\" cellspacing=\"1\">\n<thead>\n<tr class=\"header\">\n<th class=\"text-left\">Thu\u1ed9c t\u00ednh</th>\n<th class=\"text-left\">Gi\u00e1 tr\u1ecb</th>\n\n</tr>\n</thead>\n<tbody>\n<tr>\n<td class=\"first-td\">\n<p>D\u00f2ng \u0111i\u1ec7n \u0111\u1ecbnh m\u1ee9c</p>\n</td>\n<td>\n<p>20mA</p>\n</td>\n\n</tr>\n<tr>\n<td class=\"first-td\">\n                                            RoHS\n                                        </td>\n<td>\n<div class=\"display-flex flex-center pt-1 pb-1\">\n<img alt=\"ROHS\" src=\"/images/rohs.svg\" title=\"ROHS\" width=\"36\"/>\n</div>\n</td>\n\n</tr>\n<tr>\n\n</tr>\n</tbody>\n</table>\n</div>\n</div>"}, {"name": "TS-002 Ph\u00edm \u0110i\u1ec1u H\u01b0\u1edbng \u0110a \u0110i\u1ec3m", "img": "https://www.thegioiic.com/upload/medium/3032.jpg", "mfr": "OEM", "price": "3.000 \u0111/C\u00e1i", "stock": "H\u00e0ng c\u00f2n: 666", "link": "https://www.thegioiic.com/ts-002-phim-dieu-huong-da-diem", "desc": "MP4, MP5", "detail": "<div class=\"mt-4 pt-2 bg-white\">\n\n<div class=\"mt-2 text-medium-s body-tab\">\n<table border=\"1\" cellpadding=\"0\" cellspacing=\"1\">\n<thead>\n<tr class=\"header\">\n<th class=\"text-left\">Thu\u1ed9c t\u00ednh</th>\n<th class=\"text-left\">Gi\u00e1 tr\u1ecb</th>\n\n</tr>\n</thead>\n<tbody>\n<tr>\n<td class=\"first-td\">\n                                            RoHS\n                                        </td>\n<td>\n<div class=\"display-flex flex-center pt-1 pb-1\">\n<img alt=\"ROHS\" src=\"/images/rohs.svg\" title=\"ROHS\" width=\"36\"/>\n</div>\n</td>\n\n</tr>\n<tr>\n\n</tr>\n</tbody>\n</table>\n</div>\n</div>"}, {"name": "C\u00f4ng T\u1eafc \u0110i\u1ec1u H\u01b0\u1edbng 5 Chi\u1ec1u", "img": "https://www.thegioiic.com/upload/medium/8597.jpg", "mfr": "OEM", "price": "4.000 \u0111/C\u00e1i", "stock": "H\u00e0ng c\u00f2n: 321", "link": "https://www.thegioiic.com/cong-tac-dieu-huong-5-chieu", "desc": "Ph\u00edm \u0111i\u1ec1u h\u01b0\u1edbng 5 chi\u1ec1u, Rating: 20mA 12VDC", "detail": "<div class=\"mt-4 pt-2 bg-white\">\n\n<div class=\"mt-2 text-medium-s body-tab\">\n<table border=\"1\" cellpadding=\"0\" cellspacing=\"1\">\n<thead>\n<tr class=\"header\">\n<th class=\"text-left\">Thu\u1ed9c t\u00ednh</th>\n<th class=\"text-left\">Gi\u00e1 tr\u1ecb</th>\n\n</tr>\n</thead>\n<tbody>\n<tr>\n<td class=\"first-td\">\n<p>D\u00f2ng \u0111i\u1ec7n \u0111\u1ecbnh m\u1ee9c</p>\n</td>\n<td>\n<p>20mA</p>\n</td>\n\n</tr>\n<tr>\n<td class=\"first-td\">\n                                            RoHS\n                                        </td>\n<td>\n<div class=\"display-flex flex-center pt-1 pb-1\">\n<img alt=\"ROHS\" src=\"/images/rohs.svg\" title=\"ROHS\" width=\"36\"/>\n</div>\n</td>\n\n</tr>\n<tr>\n\n</tr>\n</tbody>\n</table>\n</div>\n</div>"}, {"name": "C\u00f4ng T\u1eafc Xoay 19mm 6 Ch\u00e2n 2NO 2NC C\u00f3 Ch\u00eca Kho\u00e1", "img": "https://www.thegioiic.com/upload/medium/33229.jpg", "mfr": "OEM", "price": "88.000 \u0111/C\u00e1i", "stock": "H\u1ebft h\u00e0ng", "link": "https://www.thegioiic.com/cong-tac-xoay-19mm-6-chan-2no-2nc-co-chia-khoa", "desc": "IP65, 3A 250VAC", "detail": "<div class=\"mt-4 pt-2 bg-white\">\n\n<div class=\"mt-2 text-medium-s body-tab\">\n<table border=\"1\" cellpadding=\"0\" cellspacing=\"1\">\n<thead>\n<tr class=\"header\">\n<th class=\"text-left\">Thu\u1ed9c t\u00ednh</th>\n<th class=\"text-left\">Gi\u00e1 tr\u1ecb</th>\n\n</tr>\n</thead>\n<tbody>\n<tr>\n<td class=\"first-td\">\n<p>D\u00f2ng \u0111i\u1ec7n \u0111\u1ecbnh m\u1ee9c</p>\n</td>\n<td>\n<p>3A</p>\n</td>\n\n</tr>\n<tr>\n<td class=\"first-td\">\n                                            RoHS\n                                        </td>\n<td>\n<div class=\"display-flex flex-center pt-1 pb-1\">\n<img alt=\"ROHS\" src=\"/images/rohs.svg\" title=\"ROHS\" width=\"36\"/>\n</div>\n</td>\n\n</tr>\n<tr>\n\n</tr>\n</tbody>\n</table>\n</div>\n</div>"}, {"name": "C\u00f4ng T\u1eafc Xoay 19mm 3 Ch\u00e2n 1NO 1NC C\u00f3 Ch\u00eca Kho\u00e1", "img": "https://www.thegioiic.com/upload/medium/33229.jpg", "mfr": "OEM", "price": "82.000 \u0111/C\u00e1i", "stock": "H\u1ebft h\u00e0ng", "link": "https://www.thegioiic.com/cong-tac-xoay-19mm-3-chan-1no-1nc-co-chia-khoa", "desc": "IP65, 3A 250VAC", "detail": "<div class=\"mt-4 pt-2 bg-white\">\n\n<div class=\"mt-2 text-medium-s body-tab\">\n<table border=\"1\" cellpadding=\"0\" cellspacing=\"1\">\n<thead>\n<tr class=\"header\">\n<th class=\"text-left\">Thu\u1ed9c t\u00ednh</th>\n<th class=\"text-left\">Gi\u00e1 tr\u1ecb</th>\n\n</tr>\n</thead>\n<tbody>\n<tr>\n<td class=\"first-td\">\n<p>D\u00f2ng \u0111i\u1ec7n \u0111\u1ecbnh m\u1ee9c</p>\n</td>\n<td>\n<p>3A</p>\n</td>\n\n</tr>\n<tr>\n<td class=\"first-td\">\n                                            RoHS\n                                        </td>\n<td>\n<div class=\"display-flex flex-center pt-1 pb-1\">\n<img alt=\"ROHS\" src=\"/images/rohs.svg\" title=\"ROHS\" width=\"36\"/>\n</div>\n</td>\n\n</tr>\n<tr>\n\n</tr>\n</tbody>\n</table>\n</div>\n</div>"}, {"name": "C\u00f4ng T\u1eafc Xoay 16mm 6 Ch\u00e2n 2NO 2NC C\u00f3 Ch\u00eca Kho\u00e1", "img": "https://www.thegioiic.com/upload/medium/33229.jpg", "mfr": "OEM", "price": "85.000 \u0111/C\u00e1i", "stock": "H\u1ebft h\u00e0ng", "link": "https://www.thegioiic.com/cong-tac-xoay-16mm-6-chan-2no-2nc-co-chia-khoa", "desc": "IP65, 3A 250VAC", "detail": "<div class=\"mt-4 pt-2 bg-white\">\n\n<div class=\"mt-2 text-medium-s body-tab\">\n<table border=\"1\" cellpadding=\"0\" cellspacing=\"1\">\n<thead>\n<tr class=\"header\">\n<th class=\"text-left\">Thu\u1ed9c t\u00ednh</th>\n<th class=\"text-left\">Gi\u00e1 tr\u1ecb</th>\n\n</tr>\n</thead>\n<tbody>\n<tr>\n<td class=\"first-td\">\n<p>D\u00f2ng \u0111i\u1ec7n \u0111\u1ecbnh m\u1ee9c</p>\n</td>\n<td>\n<p>3A</p>\n</td>\n\n</tr>\n<tr>\n<td class=\"first-td\">\n                                            RoHS\n                                        </td>\n<td>\n<div class=\"display-flex flex-center pt-1 pb-1\">\n<img alt=\"ROHS\" src=\"/images/rohs.svg\" title=\"ROHS\" width=\"36\"/>\n</div>\n</td>\n\n</tr>\n<tr>\n\n</tr>\n</tbody>\n</table>\n</div>\n</div>"}, {"name": "C\u00f4ng T\u1eafc Xoay 16mm 3 Ch\u00e2n 1NO 1NC C\u00f3 Ch\u00eca Kho\u00e1", "img": "https://www.thegioiic.com/upload/medium/33229.jpg", "mfr": "OEM", "price": "79.000 \u0111/C\u00e1i", "stock": "H\u1ebft h\u00e0ng", "link": "https://www.thegioiic.com/cong-tac-xoay-16mm-3-chan-1no-1nc-co-chia-khoa", "desc": "IP65, 3A 250VAC", "detail": "<div class=\"mt-4 pt-2 bg-white\">\n\n<div class=\"mt-2 text-medium-s body-tab\">\n<table border=\"1\" cellpadding=\"0\" cellspacing=\"1\">\n<thead>\n<tr class=\"header\">\n<th class=\"text-left\">Thu\u1ed9c t\u00ednh</th>\n<th class=\"text-left\">Gi\u00e1 tr\u1ecb</th>\n\n</tr>\n</thead>\n<tbody>\n<tr>\n<td class=\"first-td\">\n<p>D\u00f2ng \u0111i\u1ec7n \u0111\u1ecbnh m\u1ee9c</p>\n</td>\n<td>\n<p>3A</p>\n</td>\n\n</tr>\n<tr>\n<td class=\"first-td\">\n                                            RoHS\n                                        </td>\n<td>\n<div class=\"display-flex flex-center pt-1 pb-1\">\n<img alt=\"ROHS\" src=\"/images/rohs.svg\" title=\"ROHS\" width=\"36\"/>\n</div>\n</td>\n\n</tr>\n<tr>\n\n</tr>\n</tbody>\n</table>\n</div>\n</div>"}, {"name": "C\u00f4ng T\u1eafc Xoay 22mm 6 Ch\u00e2n 2NO 2NC Kh\u00f4ng Ch\u00eca Kho\u00e1", "img": "https://www.thegioiic.com/upload/medium/33229.jpg", "mfr": "OEM", "price": "88.000 \u0111/C\u00e1i", "stock": "H\u1ebft h\u00e0ng", "link": "https://www.thegioiic.com/cong-tac-xoay-22mm-6-chan-2no-2nc-khong-chia-khoa", "desc": "IP65, 3A 250VAC", "detail": "<div class=\"mt-4 pt-2 bg-white\">\n\n<div class=\"mt-2 text-medium-s body-tab\">\n<table border=\"1\" cellpadding=\"0\" cellspacing=\"1\">\n<thead>\n<tr class=\"header\">\n<th class=\"text-left\">Thu\u1ed9c t\u00ednh</th>\n<th class=\"text-left\">Gi\u00e1 tr\u1ecb</th>\n\n</tr>\n</thead>\n<tbody>\n<tr>\n<td class=\"first-td\">\n<p>D\u00f2ng \u0111i\u1ec7n \u0111\u1ecbnh m\u1ee9c</p>\n</td>\n<td>\n<p>3A</p>\n</td>\n\n</tr>\n<tr>\n<td class=\"first-td\">\n                                            RoHS\n                                        </td>\n<td>\n<div class=\"display-flex flex-center pt-1 pb-1\">\n<img alt=\"ROHS\" src=\"/images/rohs.svg\" title=\"ROHS\" width=\"36\"/>\n</div>\n</td>\n\n</tr>\n<tr>\n\n</tr>\n</tbody>\n</table>\n</div>\n</div>"}, {"name": "C\u00f4ng T\u1eafc Xoay 22mm 3 Ch\u00e2n 1NO 1NC Kh\u00f4ng Ch\u00eca Kho\u00e1", "img": "https://www.thegioiic.com/upload/medium/33229.jpg", "mfr": "OEM", "price": "88.000 \u0111/C\u00e1i", "stock": "H\u1ebft h\u00e0ng", "link": "https://www.thegioiic.com/cong-tac-xoay-22mm-3-chan-1no-1nc-khong-chia-khoa", "desc": "IP65, 3A 250VAC", "detail": "<div class=\"mt-4 pt-2 bg-white\">\n\n<div class=\"mt-2 text-medium-s body-tab\">\n<table border=\"1\" cellpadding=\"0\" cellspacing=\"1\">\n<thead>\n<tr class=\"header\">\n<th class=\"text-left\">Thu\u1ed9c t\u00ednh</th>\n<th class=\"text-left\">Gi\u00e1 tr\u1ecb</th>\n\n</tr>\n</thead>\n<tbody>\n<tr>\n<td class=\"first-td\">\n<p>D\u00f2ng \u0111i\u1ec7n \u0111\u1ecbnh m\u1ee9c</p>\n</td>\n<td>\n<p>3A</p>\n</td>\n\n</tr>\n<tr>\n<td class=\"first-td\">\n                                            RoHS\n                                        </td>\n<td>\n<div class=\"display-flex flex-center pt-1 pb-1\">\n<img alt=\"ROHS\" src=\"/images/rohs.svg\" title=\"ROHS\" width=\"36\"/>\n</div>\n</td>\n\n</tr>\n<tr>\n\n</tr>\n</tbody>\n</table>\n</div>\n</div>"}, {"name": "C\u00f4ng T\u1eafc Xoay 19mm 6 Ch\u00e2n 2NO 2NC Kh\u00f4ng Ch\u00eca Kho\u00e1", "img": "https://www.thegioiic.com/upload/medium/33229.jpg", "mfr": "OEM", "price": "88.000 \u0111/C\u00e1i", "stock": "H\u1ebft h\u00e0ng", "link": "https://www.thegioiic.com/cong-tac-xoay-19mm-6-chan-2no-2nc-khong-chia-khoa", "desc": "IP65, 3A 250VAC", "detail": "<div class=\"mt-4 pt-2 bg-white\">\n\n<div class=\"mt-2 text-medium-s body-tab\">\n<table border=\"1\" cellpadding=\"0\" cellspacing=\"1\">\n<thead>\n<tr class=\"header\">\n<th class=\"text-left\">Thu\u1ed9c t\u00ednh</th>\n<th class=\"text-left\">Gi\u00e1 tr\u1ecb</th>\n\n</tr>\n</thead>\n<tbody>\n<tr>\n<td class=\"first-td\">\n<p>D\u00f2ng \u0111i\u1ec7n \u0111\u1ecbnh m\u1ee9c</p>\n</td>\n<td>\n<p>3A</p>\n</td>\n\n</tr>\n<tr>\n<td class=\"first-td\">\n                                            RoHS\n                                        </td>\n<td>\n<div class=\"display-flex flex-center pt-1 pb-1\">\n<img alt=\"ROHS\" src=\"/images/rohs.svg\" title=\"ROHS\" width=\"36\"/>\n</div>\n</td>\n\n</tr>\n<tr>\n\n</tr>\n</tbody>\n</table>\n</div>\n</div>"}]