[{"name": "B\u1ed9t S\u1eaft FeCl3", "img": "https://www.thegioiic.com/upload/medium/6230.jpg", "mfr": "OEM", "price": "13.000 \u0111/B\u1ecbch", "stock": "H\u00e0ng c\u00f2n: 61", "link": "https://www.thegioiic.com/bot-sat-fecl3", "desc": "B\u1ed9t s\u1eaft \u0103n m\u00f2n m\u1ea1ch, FeCl3", "detail": "<div class=\"mt-4 pt-2 bg-white\">\n\n<div class=\"mt-2 text-medium-s body-tab\">\n<table border=\"1\" cellpadding=\"0\" cellspacing=\"1\">\n<thead>\n<tr class=\"header\">\n<th class=\"text-left\">Thu\u1ed9c t\u00ednh</th>\n<th class=\"text-left\">Gi\u00e1 tr\u1ecb</th>\n\n</tr>\n</thead>\n<tbody>\n<tr>\n<td class=\"first-td\">\n<p>Lo\u1ea1i</p>\n</td>\n<td>\n<p>B\u1ed9t</p>\n</td>\n\n</tr>\n<tr>\n\n</tr>\n</tbody>\n</table>\n</div>\n</div>"}, {"name": "M\u1ef1c C\u1ea3m Quang Blue Oil 100g", "img": "https://www.thegioiic.com/upload/medium/9482.jpg", "mfr": "OEM", "price": "77.000 \u0111/L\u1ecd", "stock": "H\u00e0ng c\u00f2n: 28", "link": "https://www.thegioiic.com/muc-cam-quang-blue-oil-100g", "desc": "Thay th\u1ebf phim c\u1ea3m quang", "detail": "<div class=\"mt-4 pt-2 bg-white\">\n\n<div class=\"mt-2 text-medium-s body-tab\">\n<table border=\"1\" cellpadding=\"0\" cellspacing=\"1\">\n<thead>\n<tr class=\"header\">\n<th class=\"text-left\">Thu\u1ed9c t\u00ednh</th>\n<th class=\"text-left\">Gi\u00e1 tr\u1ecb</th>\n\n</tr>\n</thead>\n<tbody>\n<tr>\n<td class=\"first-td\">\n<p>Lo\u1ea1i</p>\n</td>\n<td>\n<p>M\u1ef1c</p>\n</td>\n\n</tr>\n<tr>\n<td class=\"first-td\">\n                                            RoHS\n                                        </td>\n<td>\n<div class=\"display-flex flex-center pt-1 pb-1\">\n<img alt=\"ROHS\" src=\"/images/rohs.svg\" title=\"ROHS\" width=\"36\"/>\n</div>\n</td>\n\n</tr>\n<tr>\n\n</tr>\n</tbody>\n</table>\n</div>\n</div>"}, {"name": "Dung D\u1ecbch Pha M\u1ef1c C\u1ea3m Quang 100ml", "img": "https://www.thegioiic.com/upload/medium/22212.jpg", "mfr": "OEM", "price": "44.000 \u0111/L\u1ecd", "stock": "H\u00e0ng c\u00f2n: 26", "link": "https://www.thegioiic.com/dung-dich-pha-muc-cam-quang-100ml", "desc": "L\u1ecd 100ml", "detail": "<div class=\"mt-4 pt-2 bg-white\">\n\n<div class=\"mt-2 text-medium-s body-tab\">\n<table border=\"1\" cellpadding=\"0\" cellspacing=\"1\">\n<thead>\n<tr class=\"header\">\n<th class=\"text-left\">Thu\u1ed9c t\u00ednh</th>\n<th class=\"text-left\">Gi\u00e1 tr\u1ecb</th>\n\n</tr>\n</thead>\n<tbody>\n<tr>\n<td class=\"first-td\">\n<p>Lo\u1ea1i</p>\n</td>\n<td>\n<p>Dung d\u1ecbch</p>\n</td>\n\n</tr>\n<tr>\n\n</tr>\n</tbody>\n</table>\n</div>\n</div>"}, {"name": "Chai Dung D\u1ecbch Axeton 350ml", "img": "https://www.thegioiic.com/upload/medium/12756.jpg", "mfr": "OEM", "price": "32.000 \u0111/Chai", "stock": "H\u00e0ng c\u00f2n: 21", "link": "https://www.thegioiic.com/chai-dung-dich-axeton-350ml", "desc": "D\u00f9ng \u0111\u1ec3 v\u1ec7 sinh m\u1ea1ch in, 350ml", "detail": "<div class=\"mt-4 pt-2 bg-white\">\n\n<div class=\"mt-2 text-medium-s body-tab\">\n<table border=\"1\" cellpadding=\"0\" cellspacing=\"1\">\n<thead>\n<tr class=\"header\">\n<th class=\"text-left\">Thu\u1ed9c t\u00ednh</th>\n<th class=\"text-left\">Gi\u00e1 tr\u1ecb</th>\n\n</tr>\n</thead>\n<tbody>\n<tr>\n<td class=\"first-td\">\n<p>Lo\u1ea1i</p>\n</td>\n<td>\n<p>Dung d\u1ecbch</p>\n</td>\n\n</tr>\n<tr>\n\n</tr>\n</tbody>\n</table>\n</div>\n</div>"}, {"name": "M\u1ef1c UV Ph\u1ee7 PCB Mechanic 10ml M\u00e0u Xanh D\u01b0\u01a1ng", "img": "https://www.thegioiic.com/upload/medium/32620.jpg", "mfr": "Mechanic", "price": "37.000 \u0111/\u1ed0ng", "stock": "H\u00e0ng c\u00f2n: 16", "link": "https://www.thegioiic.com/muc-uv-phu-pcb-mechanic-10ml-mau-xanh-duong", "desc": "M\u00e0u Xanh, ch\u1ed1ng oxy h\u00f3a, dung t\u00edch: 10ml", "detail": "<div class=\"mt-4 pt-2 bg-white\">\n\n<div class=\"mt-2 text-medium-s body-tab\">\n<table border=\"1\" cellpadding=\"0\" cellspacing=\"1\">\n<thead>\n<tr class=\"header\">\n<th class=\"text-left\">Thu\u1ed9c t\u00ednh</th>\n<th class=\"text-left\">Gi\u00e1 tr\u1ecb</th>\n\n</tr>\n</thead>\n<tbody>\n<tr>\n<td class=\"first-td\">\n<p>Lo\u1ea1i</p>\n</td>\n<td>\n<p>M\u1ef1c</p>\n</td>\n\n</tr>\n<tr>\n<td class=\"first-td\">\n                                            RoHS\n                                        </td>\n<td>\n<div class=\"display-flex flex-center pt-1 pb-1\">\n<img alt=\"ROHS\" src=\"/images/rohs.svg\" title=\"ROHS\" width=\"36\"/>\n</div>\n</td>\n\n</tr>\n<tr>\n\n</tr>\n</tbody>\n</table>\n</div>\n</div>"}, {"name": "M\u1ef1c UV Ph\u1ee7 PCB Mechanic 10ml M\u00e0u \u0110en", "img": "https://www.thegioiic.com/upload/medium/32622.jpg", "mfr": "Mechanic", "price": "37.000 \u0111/\u1ed0ng", "stock": "H\u00e0ng c\u00f2n: 9", "link": "https://www.thegioiic.com/muc-uv-phu-pcb-mechanic-10ml-mau-den", "desc": "M\u00e0u \u0111en, ch\u1ed1ng oxy h\u00f3a, dung t\u00edch: 10ml", "detail": "<div class=\"mt-4 pt-2 bg-white\">\n\n<div class=\"mt-2 text-medium-s body-tab\">\n<table border=\"1\" cellpadding=\"0\" cellspacing=\"1\">\n<thead>\n<tr class=\"header\">\n<th class=\"text-left\">Thu\u1ed9c t\u00ednh</th>\n<th class=\"text-left\">Gi\u00e1 tr\u1ecb</th>\n\n</tr>\n</thead>\n<tbody>\n<tr>\n<td class=\"first-td\">\n<p>Lo\u1ea1i</p>\n</td>\n<td>\n<p>M\u1ef1c</p>\n</td>\n\n</tr>\n<tr>\n<td class=\"first-td\">\n                                            RoHS\n                                        </td>\n<td>\n<div class=\"display-flex flex-center pt-1 pb-1\">\n<img alt=\"ROHS\" src=\"/images/rohs.svg\" title=\"ROHS\" width=\"36\"/>\n</div>\n</td>\n\n</tr>\n<tr>\n\n</tr>\n</tbody>\n</table>\n</div>\n</div>"}, {"name": "B\u1ed9t \u0102n M\u00f2n L\u00e0m M\u1ea1ch \u0110i\u1ec7n PCB 185g Blue", "img": "https://www.thegioiic.com/upload/medium/30795.jpg", "mfr": "OEM", "price": "48.000 \u0111/G\u00f3i", "stock": "H\u00e0ng c\u00f2n: 6", "link": "https://www.thegioiic.com/bot-an-mon-lam-mach-dien-pcb-185g-blue", "desc": "Tr\u1ecdng l\u01b0\u1ee3ng: 185g, thay th\u1ebf FeCl3", "detail": "<div class=\"mt-4 pt-2 bg-white\">\n\n<div class=\"mt-2 text-medium-s body-tab\">\n<table border=\"1\" cellpadding=\"0\" cellspacing=\"1\">\n<thead>\n<tr class=\"header\">\n<th class=\"text-left\">Thu\u1ed9c t\u00ednh</th>\n<th class=\"text-left\">Gi\u00e1 tr\u1ecb</th>\n\n</tr>\n</thead>\n<tbody>\n<tr>\n<td class=\"first-td\">\n<p>Lo\u1ea1i</p>\n</td>\n<td>\n<p>B\u1ed9t</p>\n</td>\n\n</tr>\n<tr>\n\n</tr>\n</tbody>\n</table>\n</div>\n</div>"}, {"name": "Dung D\u1ecbch M\u1ea1 Thi\u1ebfc PCB HASL 100ml", "img": "https://www.thegioiic.com/upload/medium/2996.jpg", "mfr": "OEM", "price": "79.000 \u0111/L\u1ecd", "stock": "H\u00e0ng c\u00f2n: 6", "link": "https://www.thegioiic.com/dung-dich-ma-thiec-pcb-hasl-100ml", "desc": "Ph\u1ee7 thi\u1ebfc l\u00ean PCB", "detail": "<div class=\"mt-4 pt-2 bg-white\">\n\n<div class=\"mt-2 text-medium-s body-tab\">\n<table border=\"1\" cellpadding=\"0\" cellspacing=\"1\">\n<thead>\n<tr class=\"header\">\n<th class=\"text-left\">Thu\u1ed9c t\u00ednh</th>\n<th class=\"text-left\">Gi\u00e1 tr\u1ecb</th>\n\n</tr>\n</thead>\n<tbody>\n<tr>\n<td class=\"first-td\">\n<p>Lo\u1ea1i</p>\n</td>\n<td>\n<p>Dung d\u1ecbch</p>\n</td>\n\n</tr>\n<tr>\n<td class=\"first-td\">\n                                            RoHS\n                                        </td>\n<td>\n<div class=\"display-flex flex-center pt-1 pb-1\">\n<img alt=\"ROHS\" src=\"/images/rohs.svg\" title=\"ROHS\" width=\"36\"/>\n</div>\n</td>\n\n</tr>\n<tr>\n\n</tr>\n</tbody>\n</table>\n</div>\n</div>"}, {"name": "M\u1ef1c UV Ph\u1ee7 PCB Mechanic 10ml M\u00e0u V\u00e0ng", "img": "https://www.thegioiic.com/upload/medium/32618.jpg", "mfr": "Mechanic", "price": "37.000 \u0111/\u1ed0ng", "stock": "H\u00e0ng c\u00f2n: 5", "link": "https://www.thegioiic.com/muc-uv-phu-pcb-mechanic-10ml-mau-vang", "desc": "M\u00e0u v\u00e0ng, ch\u1ed1ng oxy h\u00f3a, dung t\u00edch: 10ml", "detail": "<div class=\"mt-4 pt-2 bg-white\">\n\n<div class=\"mt-2 text-medium-s body-tab\">\n<table border=\"1\" cellpadding=\"0\" cellspacing=\"1\">\n<thead>\n<tr class=\"header\">\n<th class=\"text-left\">Thu\u1ed9c t\u00ednh</th>\n<th class=\"text-left\">Gi\u00e1 tr\u1ecb</th>\n\n</tr>\n</thead>\n<tbody>\n<tr>\n<td class=\"first-td\">\n<p>Lo\u1ea1i</p>\n</td>\n<td>\n<p>M\u1ef1c</p>\n</td>\n\n</tr>\n<tr>\n<td class=\"first-td\">\n                                            RoHS\n                                        </td>\n<td>\n<div class=\"display-flex flex-center pt-1 pb-1\">\n<img alt=\"ROHS\" src=\"/images/rohs.svg\" title=\"ROHS\" width=\"36\"/>\n</div>\n</td>\n\n</tr>\n<tr>\n\n</tr>\n</tbody>\n</table>\n</div>\n</div>"}, {"name": "M\u1ef1c UV Ph\u1ee7 PCB Mechanic 10ml M\u00e0u \u0110\u1ecf", "img": "https://www.thegioiic.com/upload/medium/32619.jpg", "mfr": "Mechanic", "price": "37.000 \u0111/\u1ed0ng", "stock": "H\u00e0ng c\u00f2n: 5", "link": "https://www.thegioiic.com/muc-uv-phu-pcb-mechanic-10ml-mau-do", "desc": "M\u00e0u \u0111\u1ecf, ch\u1ed1ng oxy h\u00f3a, dung t\u00edch: 10ml", "detail": "<div class=\"mt-4 pt-2 bg-white\">\n\n<div class=\"mt-2 text-medium-s body-tab\">\n<table border=\"1\" cellpadding=\"0\" cellspacing=\"1\">\n<thead>\n<tr class=\"header\">\n<th class=\"text-left\">Thu\u1ed9c t\u00ednh</th>\n<th class=\"text-left\">Gi\u00e1 tr\u1ecb</th>\n\n</tr>\n</thead>\n<tbody>\n<tr>\n<td class=\"first-td\">\n<p>Lo\u1ea1i</p>\n</td>\n<td>\n<p>M\u1ef1c</p>\n</td>\n\n</tr>\n<tr>\n<td class=\"first-td\">\n                                            RoHS\n                                        </td>\n<td>\n<div class=\"display-flex flex-center pt-1 pb-1\">\n<img alt=\"ROHS\" src=\"/images/rohs.svg\" title=\"ROHS\" width=\"36\"/>\n</div>\n</td>\n\n</tr>\n<tr>\n\n</tr>\n</tbody>\n</table>\n</div>\n</div>"}]