[{"name": "K\u1eb9p Gi\u1eef \u0110\u00e8n LED T8 B\u1eb1ng Inox", "img": "https://www.thegioiic.com/upload/medium/52176.jpg", "mfr": "OEM", "price": "1.000 \u0111/C\u00e1i", "stock": "H\u00e0ng c\u00f2n: 153", "link": "https://www.thegioiic.com/kep-giu-den-led-t8-bang-inox", "desc": "D\u1ec5 s\u1eed d\u1ee5ng, ch\u1eafc ch\u1eafn", "detail": "<div class=\"mt-4 pt-2 bg-white\">\n<h2 class=\"title-tab text-title font-500 m-0\">\n                                                    M\u00f4 t\u1ea3 s\u1ea3n ph\u1ea9m\n                                            </h2>\n<div class=\"mt-2 text-medium-s body-tab product M\u00f4 t\u1ea3 s\u1ea3n ph\u1ea9m\">\n<ul>\n<li>K\u1eb9p Gi\u1eef \u0110\u00e8n LED T8 B\u1eb1ng Inox</li>\n<li>D\u1ec5 s\u1eed d\u1ee5ng, ch\u1eafc ch\u1eafn.</li>\n</ul>\n<p><strong><img src=\"https://www.thegioiic.com/upload/large/51244.jpg\"/></strong></p>\n</div>\n</div>"}, {"name": "K\u1eb9p Gi\u1eef \u0110\u00e8n LED T8 B\u1eb1ng Nh\u1ef1a", "img": "https://www.thegioiic.com/upload/medium/17118.jpg", "mfr": "OEM", "price": "1.900 \u0111/C\u00e1i", "stock": "H\u1ebft h\u00e0ng", "link": "https://www.thegioiic.com/kep-giu-den-led-t8-bang-nhua", "desc": "Nh\u1ef1a PP h\u1ea5t l\u01b0\u1ee3ng cao", "detail": "<div class=\"mt-4 pt-2 bg-white\">\n<h2 class=\"title-tab text-title font-500 m-0\">\n                                                    M\u00f4 t\u1ea3 s\u1ea3n ph\u1ea9m\n                                            </h2>\n<div class=\"mt-2 text-medium-s body-tab product M\u00f4 t\u1ea3 s\u1ea3n ph\u1ea9m\">\n<ul>\n<li>K\u1eb9p Gi\u1eef \u0110\u00e8n LED T8 B\u1eb1ng Nh\u1ef1a</li>\n<li>Nh\u1ef1a PP h\u1ea5t l\u01b0\u1ee3ng cao</li>\n</ul>\n</div>\n</div>"}]